image_processing_ishibashi/__init__.py
image_processing_ishibashi/processing/__init__.py
image_processing_ishibashi/processing/combination.py
image_processing_ishibashi/processing/transformation.py
image_processing_ishibashi/utils/__init__.py
image_processing_ishibashi/utils/io.py
image_processing_ishibashi/utils/plot.py
image_processing_ishibashi-0.1.dist-info/METADATA
image_processing_ishibashi-0.1.dist-info/WHEEL
image_processing_ishibashi-0.1.dist-info/top_level.txt
image_processing_ishibashi-0.1.dist-info/RECORD
