Metadata-Version: 2.1
Name: image_processing_ishibashi
Version: 0.1
Summary: Image Processing Package
Home-page: https://github.com/TheoIshibashi/image-processing-package
Author: TheoShiba
Author-email: theoshiba2005@gmail.com
Requires-Python: >=3.6
Requires-Dist: matplotlib
Requires-Dist: numpy
Requires-Dist: scikit-image>=0.16.1
